Workbook

Sheet README
A1: Financial Model — README
A2: HappyPix V2 · prepared 2026-10-23 · INR unless stated · figures are planning estimates
B4: HappyPix — Complete Expenditure & Financial Model
B5: Companion to business/SCALABILITY_PLAN.md and business/UNIT_ECONOMICS.xlsx
B7: How to use this workbook
B8: 1. Open the Assumptions sheet. Every yellow cell is editable.
B9: 2. Monthly_Forecast recalculates 48 months of P&L, cash and runway.
B10: 3. Team_Costs drives the salary lines; change headcount there, not in the forecast.
B11: 4. Infrastructure holds the four growth-stage run-rates (USD), converted at the FX rate.
B12: 5. Actual_vs_Forecast is for monthly bookkeeping — paste real revenue and read the variance.
B14: Colour convention
B15: Yellow = input you may change. Grey = formula. Green = total or key result.
B17: Workbook map
B18: Assumptions — FX, ARPU, churn, fees, CAC, overheads.
... B36: python3 business/scripts/build_workbooks.py (requires openpyxl)

Sheet Summary
A1: Model Summary
A2: Key outputs. All values are formulas over Monthly_Forecast.
A4: Metric | B4: Value | C4: How to read it
A5: Total funding raised | B5: =SUM(Monthly_Forecast!C22:AX22) | C5: Founder capital + seed + bridge
A6: ARR at month 12 | B6: =Monthly_Forecast!N11*12 | C6: Annualised run-rate, year 1 exit
A7: ARR at month 24 | B7: =Monthly_Forecast!Z11*12 | C7: Annualised run-rate, year 2 exit
A8: ARR at month 36 | B8: =Monthly_Forecast!AL11*12 | C8: Annualised run-rate, year 3 exit
A9: ARR at month 48 | B9: =Monthly_Forecast!AX11*12 | C9: Annualised run-rate, year 4 exit
A10: Paying organizations at month 48 | B10: =Monthly_Forecast!AX7 | C10: ≈ 2.2 registered users each
A11: Monthly revenue at month 48 | B11: =Monthly_Forecast!AX11 | C11: One month, not annualised
A12: Monthly EBITDA at month 48 | B12: =Monthly_Forecast!AX21 | C12: Positive = self-funding
A13: Profitable months in 48 | B13: =COUNTIF(Monthly_Forecast!C21:AX21,">0") | C13: First positive month marks break-even
A14: Cumulative EBITDA (48 months) | B14: =SUM(Monthly_Forecast!C21:AX21) | C14: Total cash consumed by operations
A15: Lowest cash balance | B15: =MIN(Monthly_Forecast!C23:AX23) | C15: Must stay above zero
A16: Cash at month 48 | B16: =Monthly_Forecast!AX23 | C16: Ending liquidity
A17: Peak monthly burn | B17: =MIN(Monthly_Forecast!C21:AX21) | C17: Worst single month
A18: Total invested to date + remaining to launch | B18: =Dev_Investment!D27+Dev_Investment!D44 | C18: From the Dev_Investment sheet
A20: If any metric looks implausible, change the inputs on Monthly_Forecast (growth, churn, funding) or Assumptions (ARPU, costs) — never overwrite the calculated rows.

Sheet Assumptions
A1: Assumptions
A2: Every other sheet references these cells. Change them here, not in the model sheets.
A4: Assumption | B4: Value | C4: Unit | D4: Source / rationale
A5: FX rate | B5: 84 | C5: INR/USD | D5: 2026 planning rate
A6: Users per organization | B6: 2.2 | C6: seats | D6: Observed CRM seat average
A7: Blended ARPU | B7: 1150 | C7: INR/org/mo | D7: Mix of Basic/Pro/Premium incl. annual discounts
A8: Add-on attach rate | B8: 0.12 | C8: % of orgs | D8: ₹249 add-ons
A9: Add-on price | B9: 249 | C9: INR/mo | D9: Catalogue price
A10: Monthly logo churn | B10: 0.03 | C10: % of orgs | D10: Early-stage SaaS; improves with age
A11: Monthly expansion | B11: 0.008 | C11: % of orgs | D11: Upgrades and seat growth
A12: Payment MDR — cards | B12: 0.02 | C12: % of value | D12: Razorpay standard
A13: Payment MDR — UPI | B13: 0 | C13: % of value | D13: UPI is zero-MDR in India
A14: Card share of payments | B14: 0.35 | C14: % of value | D14: Rest is UPI
A15: GST on subscription | B15: 0.18 | C15: % | D15: India, 18%
A16: Refund / dispute rate | B16: 0.015 | C16: % of revenue | D16: Chargebacks + goodwill
... A27: Opening cash | B27: 10000000 | C27: INR | D27: Founder capital at month 1
A29: Yellow cells are inputs. All model sheets read from this block.

Sheet Dev_Investment
A1: Historical Development Investment & Remaining Launch Costs
A2: What has been spent to reach today, and what is still needed to launch commercially.
A4: Workstream | B4: Hours | C4: Rate (INR/h) | D4: Cost (INR) | E4: Notes
A5: Architecture & technical leadership | B5: 2400 | C5: 1500 | D5: =B5*C5 | E5: Multi-tenant model, pricing engine, snapshots
A6: Backend engineering | B6: 3200 | C6: 1200 | D6: =B6*C6 | E6: 23 models, 100+ endpoints, payments, S3, AI pipeline
A7: CRM frontend | B7: 1900 | C7: 1100 | D7: =B7*C7 | E7: 21 screens, permission matrix, mock backend, designer
A8: Android booth app | B8: 1500 | C8: 1200 | D8: =B8*C8 | E8: XState flow, Skia compositing, CCAPI, IPP
A9: Electron booth app | B9: 1600 | C9: 1200 | D9: =B9*C9 | E9: Hardware layer, spooler/CUPS, telemetry, IPC
A10: Public website & downloads | B10: 700 | C10: 1000 | D10: =B10*C10 | E10: Marketing, pricing, checkout, guest portal
A11: Design & branding | B11: 700 | C11: 1000 | D11: =B11*C11 | E11: Templates, UI system, brand assets
A12: QA & release engineering | B12: 900 | C12: 800 | D12: =B12*C12 | E12: Test suites, hardware verification, releases
A13: DevOps & infrastructure | B13: 500 | C13: 1400 | D13: =B13*C13 | E13: Vercel, Atlas, S3, monitoring, CI
A14: AI integration | B14: 400 | C14: 1600 | D14: =B14*C14 | E14: Groq classification, FLUX generation, IP sanitisation
A15: Project & product management | B15: 600 | C15: 900 | D15: =B15*C15 | E15: Specs, prioritisation, client feedback
A16: Total development labour | B16: =SUM(B5:B15) | D16: =SUM(D5:D15) | E16: Sunk cost to date (opportunity cost basis)
A18: Direct cash spend to date
A19: Item | B19: Months | C19: Monthly (INR) | D19: Total (INR) | E19: Notes
A20: Cloud & infrastructure | B20: 18 | C20: 18000 | D20: =B20*C20 | E20: Atlas, Vercel, S3, email/SMS
A21: AI API usage | B21: 18 | C21: 6000 | D21: =B21*C21 | E21: Groq + Together during development
A22: Domains, SSL, tooling | B22: 18 | C22: 3500 | D22: =B22*C22 | E22: Domains, GitHub, design tools
A23: Hardware prototypes | B23: 1 | C23: 385000 | D23: =B23*C23 | E23: Printers, cameras, tablets, PC builds
A24: Payment gateway setup | B24: 1 | C24: 12000 | D24: =B24*C24 | E24: KYC, integration testing
A25: Total direct spend | D25: =SUM(D20:D24)
A27: TOTAL INVESTED TO DATE | D27: =D16+D25
A30: Remaining spend to reach commercial launch
A31: Item | B31: Qty | C31: Unit cost (INR) | D31: Total (INR) | E31: Notes
A32: Code-signing certificate (Windows OV) | B32: 1 | C32: 42000 | D32: =B32*C32 | E32: Annual; required for clean installs
A33: Apple Developer Program | B33: 1 | C33: 8500 | D33: =B33*C33 | E33: Annual
A34: Notarisation tooling / certificates | B34: 1 | C34: 12000 | D34: =B34*C34 | E34: Apple Developer ID
A35: Google Play developer account | B35: 1 | C35: 2200 | D35: =B35*C35 | E35: One-time
A36: Privacy policy & terms drafting | B36: 1 | C36: 85000 | D36: =B36*C36 | E36: Counsel-reviewed for DPDP + GDPR
A37: Security review / light pen test | B37: 1 | C37: 180000 | D37: =B37*C37 | E37: Before enterprise sales
A38: Trademark filing (India, 2 classes) | B38: 1 | C38: 45000 | D38: =B38*C38 | E38: Name + logo
A39: Accounting & company compliance | B39: 12 | C39: 12000 | D39: =B39*C39 | E39: Monthly retainer, first year
A40: Launch marketing budget | B40: 1 | C40: 400000 | D40: =B40*C40 | E40: Content, ads, event presence
A41: Pilot hardware fleet (3 rigs) | B41: 3 | C41: 235000 | D41: =B41*C41 | E41: Printer + camera + PC per rig
A42: Spare media (initial stock) | B42: 1 | C42: 140000 | D42: =B42*C42 | E42: Rolls for pilots and demos
A43: Contingency (10%) | B43: 1 | C43: 0 | D43: =ROUND(SUM(D32:D42)*0.1,0) | E43: Calculated below
A44: Total remaining to launch | D44: =SUM(D32:D43)
A46: TOTAL CAPITAL REQUIRED (invested + remaining) | D46: =D27+D44

Sheet Team_Costs
A1: Team & Personnel Costs
A2: Headcount by phase. Monthly cost per role × headcount, plus employer overhead.
A4: Role | B4: Monthly (INR) | C4: Phase A M1–6 | D4: Phase B M7–12 | E4: Phase C M13–24 | F4: Phase D M25–36 | G4: Phase A cost | H4: Phase B cost | I4: Phase C cost | J4: Phase D cost / notes
A5: Founder / CEO | B5: 200000 | C5: 1 | D5: 1 | E5: 1 | F5: 1 | G5: =$B5*C5 | H5: =$B5*D5 | I5: =$B5*E5 | J5: Fundraising, sales, product direction
A6: Engineering Lead | B6: 260000 | C6: 1 | D6: 1 | E6: 1 | F6: 1 | G6: =$B6*C6 | H6: =$B6*D6 | I6: =$B6*E6 | J6: Architecture, reviews, releases
A7: Backend Engineer | B7: 160000 | C7: 2 | D7: 2 | E7: 3 | F7: 4 | G7: =$B7*C7 | H7: =$B7*D7 | I7: =$B7*E7 | J7: API, payments, storage, integrations
A8: Frontend Engineer | B8: 140000 | C8: 1 | D8: 1 | E8: 1 | F8: 2 | G8: =$B8*C8 | H8: =$B8*D8 | I8: =$B8*E8 | J8: CRM + website
A9: Mobile Engineer (Android) | B9: 170000 | C9: 0 | D9: 1 | E9: 1 | F9: 1 | G9: =$B9*C9 | H9: =$B9*D9 | I9: =$B9*E9 | J9: RN booth app, native modules
A10: Desktop Engineer (Electron) | B10: 170000 | C10: 1 | D10: 1 | E10: 1 | F10: 1 | G10: =$B10*C10 | H10: =$B10*D10 | I10: =$B10*E10 | J10: Windows/macOS kiosk, printer stack
A11: QA Engineer | B11: 100000 | C11: 1 | D11: 1 | E11: 1 | F11: 2 | G11: =$B11*C11 | H11: =$B11*D11 | I11: =$B11*E11 | J11: Manual + automated, hardware verification
A12: Designer | B12: 130000 | C12: 0 | D12: 1 | E12: 1 | F12: 1 | G12: =$B12*C12 | H12: =$B12*D12 | I12: =$B12*E12 | J12: Templates, UI, brand
A13: Product Manager | B13: 200000 | C13: 0 | D13: 0 | E13: 0 | F13: 1 | G13: =$B13*C13 | H13: =$B13*D13 | I13: =$B13*E13 | J13: Roadmap, specs, prioritisation
A14: DevOps / SRE | B14: 210000 | C14: 0 | D14: 0 | E14: 1 | F14: 1 | G14: =$B14*C14 | H14: =$B14*D14 | I14: =$B14*E14 | J14: Infra, monitoring, DR
A15: Sales / Partnerships | B15: 110000 | C15: 0 | D15: 1 | E15: 2 | F15: 3 | G15: =$B15*C15 | H15: =$B15*D15 | I15: =$B15*E15 | J15: Base only; commission in Marketing_Support
A16: Support Associate | B16: 42000 | C16: 2 | D16: 3 | E16: 4 | F16: 5 | G16: =$B16*C16 | H16: =$B16*D16 | I16: =$B16*E16 | J16: Ticket handling, onboarding
... A18: Finance / Accounts | B18: 70000 | C18: 1 | D18: 1 | E18: 1 | F18: 1 | G18: =$B18*C18 | H18: =$B18*D18 | I18: =$B18*E18 | J18: Reconciliation, GST, payroll
A19: Headcount | C19: =SUM(C5:C18) | D19: =SUM(D5:D18) | E19: =SUM(E5:E18) | F19: =SUM(F5:F18) | J19: Total people per phase
A20: Base salary cost / month | G20: =SUM(G5:G18) | H20: =SUM(H5:H18) | I20: =SUM(I5:I18) | J20: Add the Phase D total in column J below
A21: Employer overhead (15%) | G21: =G20*Assumptions!$B$26 | H21: =H20*Assumptions!$B$26 | I21: =I20*Assumptions!$B$26 | J21: Benefits, equipment, software seats
A22: TOTAL TEAM COST / MONTH | G22: =G20+G21 | H22: =H20+H21 | I22: =I20+I21 | J22: Phase D is calculated on the Phase D sheet of the forecast
A24: Phase D detail (months 25–36)
A25: Phase D headcount | B25: =SUM(F5:F18)
A26: Phase D total monthly cost | B26: =SUMPRODUCT($B$5:$B$18,F5:F18)*(1+Assumptions!$B$26)

Sheet Infrastructure
A1: Infrastructure & Cloud Costs
A2: Monthly run-rate by growth stage. Aligned with business/SCALABILITY_PLAN.md.
A4: Service | B4: Unit | C4: Stage 1 10K users | D4: Stage 2 100K | E4: Stage 3 1M | F4: Stage 4 10M | G4: Configuration / notes
A5: Vercel / edge & compute | B5: USD/mo | C5: 250 | D5: 2500 | E5: 18000 | F5: 120000 | G5: Functions, edges, bandwidth
A6: MongoDB Atlas | B6: USD/mo | C6: 450 | D6: 4500 | E6: 35000 | F6: 250000 | G6: M40 → M60 → sharded M80+ → multi-region
A7: AWS S3 storage | B7: USD/mo | C7: 620 | D7: 5800 | E7: 42000 | F7: 380000 | G7: Lifecycle tiering assumed at stages 2+
A8: CDN / egress | B8: USD/mo | C8: 280 | D8: 5200 | E8: 45000 | F8: 320000 | G8: CloudFront; variants reduce payload
A9: Redis / cache | B9: USD/mo | C9: 0 | D9: 600 | E9: 3000 | F9: 12000 | G9: Hot reads: plans, gallery page 1
A10: Queues / streaming / workers | B10: USD/mo | C10: 0 | D10: 1000 | E10: 11000 | F10: 60000 | G10: SQS/BullMQ → Kafka → worker fleet
A11: Monitoring, logs, tracing | B11: USD/mo | C11: 100 | D11: 800 | E11: 6000 | F11: 40000 | G11: Sentry/Logtail/Datadog class
A12: Email + SMS | B12: USD/mo | C12: 150 | D12: 1200 | E12: 8000 | F12: 50000 | G12: SendGrid + Twilio
A13: AI providers | B13: USD/mo | C13: 250 | D13: 2000 | E13: 15000 | F13: 100000 | G13: Groq + Together FLUX, credit-capped
A14: Data warehouse | B14: USD/mo | C14: 0 | D14: 0 | E14: 3000 | F14: 30000 | G14: Analytics off the OLTP database
A15: Domains, SSL, secrets, misc | B15: USD/mo | C15: 100 | D15: 500 | E15: 6000 | F15: 20000 | G15: Registrar, vault, certificates
A16: TOTAL / month (USD) | C16: =SUM(C5:C15) | D16: =SUM(D5:D15) | E16: =SUM(E5:E15) | F16: =SUM(F5:F15)
A17: TOTAL / month (INR) | C17: =C16*Assumptions!$B$5 | D17: =D16*Assumptions!$B$5 | E17: =E16*Assumptions!$B$5 | F17: =F16*Assumptions!$B$5
A18: TOTAL / year (INR) | C18: =C17*12 | D18: =D17*12 | E18: =E17*12 | F18: =F17*12
A20: Volume drivers used for the per-session figures
A21: Sessions / month | C21: 490909 | D21: 4909091 | E21: 49090909 | F21: 490909091
A22: Infrastructure cost / session (INR) | C22: =C17/C21 | D22: =D17/D21 | E22: =E17/E21 | F22: =F17/F21
A23: Infrastructure cost / session (USD) | C23: =C16/C21 | D23: =D16/D21 | E23: =E16/E21 | F23: =F16/F21

Sheet Tools_Subscriptions
A1: Tools, Subscriptions & One-off Purchases
A2: Recurring software, licences and capital items. Renewal owner is in HANDOVER_REGISTER.xlsx.
A4: Item | B4: Category | C4: Cost | D4: Billing | E4: Annual (INR) | F4: Notes
A5: GitHub Team | B5: Development | C5: 3200 | D5: monthly | E5: =C5*12 | F5: Repos, Actions, secrets
A6: Vercel Pro (4 projects) | B6: Hosting | C6: 17000 | D6: monthly | E6: =C6*12 | F6: Includes team seats
A7: MongoDB Atlas | B7: Database | C7: 38000 | D7: monthly | E7: =C7*12 | F7: Stage 1 tier
A8: AWS (S3 + CloudFront) | B8: Storage | C8: 52000 | D8: monthly | E8: =C8*12 | F8: Stage 1 estimate
A9: Cloudflare (DNS/WAF) | B9: Network | C9: 1700 | D9: monthly | E9: =C9*12 | F9: Pro plan
A10: Sentry | B10: Monitoring | C10: 4200 | D10: monthly | E10: =C10*12 | F10: Error tracking
A11: Logtail / Better Stack | B11: Monitoring | C11: 2500 | D11: monthly | E11: =C11*12 | F11: Logs + uptime
A12: SendGrid | B12: Comms | C12: 3400 | D12: monthly | E12: =C12*12 | F12: Transactional email
A13: Twilio | B13: Comms | C13: 8400 | D13: monthly | E13: =C13*12 | F13: SMS, India DLT
A14: Razorpay | B14: Payments | C14: 0 | D14: per-transaction | E14: 0 | F14: MDR modelled in Payments_Fees
A15: Google Workspace (10 seats) | B15: Productivity | C15: 12000 | D15: monthly | E15: =C15*12 | F15: Email + docs
A16: Figma | B16: Design | C16: 3800 | D16: monthly | E16: =C16*12 | F16: Team plan
A17: Windows code-signing certificate | B17: Legal/Signing | C17: 42000 | D17: annual | E17: =C17 | F17: SmartScreen reputation
A18: Apple Developer Program | B18: Legal/Signing | C18: 8500 | D18: annual | E18: =C18 | F18: macOS distribution
A19: Google Play developer account | B19: Legal/Signing | C19: 2200 | D19: one-time | E19: =C19 | F19: Android distribution
A20: DNP CyStat / printer drivers | B20: Hardware | C20: 0 | D20: bundled | E20: 0 | F20: Ships with vendor drivers
A21: Accountant retainer | B21: Finance | C21: 12000 | D21: monthly | E21: =C21*12 | F21: GST, payroll, filings
A22: Legal retainer | B22: Legal/Signing | C22: 15000 | D22: monthly | E22: =C22*12 | F22: Contracts, privacy, disputes
A23: D&O / liability insurance | B23: Legal/Signing | C23: 18000 | D23: annual | E23: =C23 | F23: Recommended before enterprise
A24: Domain renewals (3) | B24: Network | C24: 4500 | D24: annual | E24: =C24 | F24: happypix.in + subdomains
A25: TOTAL | E25: =SUM(E5:E24) | F25: Annualised run-rate (excludes transaction-based fees)

Sheet Payments_Fees
A1: Payments, Fees, Taxes & Compliance Costs
A2: Transaction economics and the recurring cost of being a compliant business.
A4: Item | B4: Basis | C4: Rate / amount | D4: Annual impact (INR) | E4: Notes
A5: Subscription revenue (year 1) | B5: INR | C5: 12000000 | D5: =C5
A6: Payment gateway MDR (blended) | B6: % of revenue | C6: =Assumptions!$B$12*Assumptions!$B$14+Assumptions!$B$13*(1-Assumptions!$B$14) | D6: =C5*C6 | E6: Cards 2%, UPI 0% — weighted by card share
A7: Refunds & goodwill | B7: % of revenue | C7: 0.015 | D7: =C5*C7 | E7: 1.5% provision for refunds and disputes
A8: GST on subscriptions (collected, not cost) | B8: % of revenue | C8: 0.18 | D8: =C5*C8 | E8: Pass-through liability; shown for completeness
A9: Chargeback fees | B9: count × fee | C9: 24 | D9: =C9*Assumptions!$B$17 | E9: Estimated annual dispute count × ₹500
A11: Compliance & professional costs
A12: Item | B12: Frequency | C12: Cost per period | D12: Annual (INR) | E12: Notes
A13: Statutory audit / CA retainer | B13: monthly | C13: 12000 | D13: =C13*12 | E13: GST, TDS, payroll, filings
A14: Company secretarial | B14: annual | C14: 25000 | D14: =C14 | E14: ROC filings, board minutes
A15: Privacy policy & ToS updates | B15: annual | C15: 40000 | D15: =C15 | E15: Counsel review
A16: Security review | B16: annual | C16: 180000 | D16: =C16 | E16: Annual light pen test
A17: Insurance (liability + cyber) | B17: annual | C17: 55000 | D17: =C17 | E17: Recommended for enterprise deals
A18: Trademark renewals (amortised) | B18: annual | C18: 9000 | D18: =C18 | E18: 10-year filings amortised
A19: PCI self-assessment support | B19: annual | C19: 30000 | D19: =C19 | E19: Questionnaire + evidence
A20: Data protection officer (part-time) | B20: monthly | C20: 25000 | D20: =C20*12 | E20: If scale requires it
A21: Total compliance | D21: =SUM(D13:D20)
A23: TOTAL PAYMENT + COMPLIANCE COST | D23: =D6+D7+D9+D21
A24: GST collected is excluded from the total — it is a pass-through liability, not a cost.

Sheet Marketing_Support
A1: Marketing, Sales, Support & Hardware Replacement
A2: The costs that actually decide whether a photobooth SaaS makes money.
A4: Item | B4: Driver | C4: Unit cost (INR) | D4: Annual (INR) | E4: Notes
A5: New organizations per year | B5: target | C5: 420
A6: Blended CAC | B6: per org | C6: 6000 | D6: =C5*C6 | E6: Content, ads, events, partner commission
A7: Marketing tooling & content | B7: monthly | C7: 35000 | D7: =C7*12 | E7: CRM for sales, email, design, video
A8: Event presence (trade shows, showcases) | B8: annual | C8: 350000 | D8: =C8 | E8: 3–4 showcases per year
A9: Support cost per organization | B9: monthly | C9: 180 | D9: =C9*12*900 | E9: Loaded support cost × 900 average active orgs
A10: Onboarding & training (per new org) | B10: per org | C10: 900 | D10: =C5*C10 | E10: Setup call, template help, hardware guidance
A11: Hardware replacement provision | B11: % of fleet value | C11: 0.06 | D11: =3800000*C11 | E11: 6% of ₹38L demo/pilot fleet value per year
A12: Spare media stock | B12: annual | C12: 140000 | D12: =C12 | E12: Rolls for demos, pilots and replacements
A13: Subtotal | D13: =SUM(D5:D12)
A14: Contingency (8%) | D14: =D13*Assumptions!$B$25
A15: TOTAL | D15: =D13*1.08

Sheet Monthly_Forecast
A1: 48-Month Forecast (P&L, Cash & Runway)
A2: New orgs, churn, funding and cash are inputs (yellow). Every other line is calculated.
A4: Line item | B4: Unit | C4: M1 | D4: M2 | E4: M3 | F4: M4 | G4: M5 | H4: M6 | I4: M7 | J4: M8 | K4: M9 | L4: M10 | M4: M11 | N4: M12 | O4: M13 | P4: M14 | Q4: M15 | R4: M16 | S4: M17 | T4: M18 | U4: M19 | V4: M20 | W4: M21 | X4: M22 | Y4: M23 | Z4: M24 | AA4: M25 | AB4: M26 | AC4: M27 | AD4: M28 | AE4: M29 | AF4: M30 | AG4: M31 | AH4: M32 | AI4: M33 | AJ4: M34 | AK4: M35 | AL4: M36 | AM4: M37 | AN4: M38 | AO4: M39 | AP4: M40 | AQ4: M41 | AR4: M42 | AS4: M43 | AT4: M44 | AU4: M45 | AV4: M46 | AW4: M47 | AX4: M48
A5: New orgs | B5: orgs | C5: 28 | D5: 34 | E5: 39 | F5: 44 | G5: 50 | H5: 56 | I5: 61 | J5: 66 | K5: 72 | L5: 78 | M5: 83 | N5: 88 | O5: 94 | P5: 100 | Q5: 105 | R5: 110 | S5: 116 | T5: 122 | U5: 127 | V5: 132 | W5: 138 | X5: 144 | Y5: 149 | Z5: 154 | AA5: 160 | AB5: 166 | AC5: 171 | AD5: 176 | AE5: 182 | AF5: 188 | AG5: 193 | AH5: 198 | AI5: 204 | AJ5: 210 | AK5: 215 | AL5: 220 | AM5: 226 | AN5: 232 | AO5: 237 | AP5: 242 | AQ5: 248 | AR5: 254 | AS5: 259 | AT5: 264 | AU5: 270 | AV5: 276 | AW5: 281 | AX5: 286
A6: Churn % | B6: % | C6: 0.034 | D6: 0.03368 | E6: 0.03336 | F6: 0.03304 | G6: 0.03272 | H6: 0.0324 | I6: 0.03208 | J6: 0.03176 | K6: 0.03144 | L6: 0.03112 | M6: 0.0308 | N6: 0.03048 | O6: 0.03016 | P6: 0.02984 | Q6: 0.02952 | R6: 0.0292 | S6: 0.02888 | T6: 0.02856 | U6: 0.02824 | V6: 0.02792 | W6: 0.0276 | X6: 0.02728 | Y6: 0.02696 | Z6: 0.02664 | AA6: 0.02632 | AB6: 0.026 | AC6: 0.02568 | AD6: 0.02536 | AE6: 0.02504 | AF6: 0.02472 | AG6: 0.0244 | AH6: 0.02408 | AI6: 0.02376 | AJ6: 0.02344 | AK6: 0.02312 | AL6: 0.0228 | AM6: 0.02248 | AN6: 0.02216 | AO6: 0.02184 | AP6: 0.02152 | AQ6: 0.0212 | AR6: 0.02088 | AS6: 0.02056 | AT6: 0.02024 | AU6: 0.01992 | AV6: 0.0196 | AW6: 0.01928 | AX6: 0.019
A7: Active orgs (end) | B7: orgs | C7: =C5*(1-C6) | D7: =C7*(1-D6)+D5 | E7: =D7*(1-E6)+E5 | F7: =E7*(1-F6)+F5 | G7: =F7*(1-G6)+G5 | H7: =G7*(1-H6)+H5 | I7: =H7*(1-I6)+I5 | J7: =I7*(1-J6)+J5 | K7: =J7*(1-K6)+K5 | ... AX7: =AW7*(1-AX6)+AX5
A8: ARPU | B8: INR | C8: =Assumptions!$B$7*(1+0.0018*(1-1)) | D8: =Assumptions!$B$7*(1+0.0018*(2-1)) | E8: =Assumptions!$B$7*(1+0.0018*(3-1)) | F8: =Assumptions!$B$7*(1+0.0018*(4-1)) | G8: =Assumptions!$B$7*(1+0.0018*(5-1)) | H8: =Assumptions!$B$7*(1+0.0018*(6-1)) | I8: =Assumptions!$B$7*(1+0.0018*(7-1)) | J8: =Assumptions!$B$7*(1+0.0018*(8-1)) | K8: =Assumptions!$B$7*(1+0.0018*(9-1)) | L8: =Assumptions!$B$7*(1+0.0018*(10-1)) | M8: =Assumptions!$B$7*(1+0.0018*(11-1)) | N8: =Assumptions!$B$7*(1+0.0018*(12-1)) | O8: =Assumptions!$B$7*(1+0.0018*(13-1)) | P8: =Assumptions!$B$7*(1+0.0018*(14-1)) | Q8: =Assumptions!$B$7*(1+0.0018*(15-1)) | R8: =Assumptions!$B$7*(1+0.0018*(16-1)) | S8: =Assumptions!$B$7*(1+0.0018*(17-1)) | T8: =Assumptions!$B$7*(1+0.0018*(18-1)) | U8: =Assumptions!$B$7*(1+0.0018*(19-1)) | V8: =Assumptions!$B$7*(1+0.0018*(20-1)) | W8: =Assumptions!$B$7*(1+0.0018*(21-1)) | X8: =Assumptions!$B$7*(1+0.0018*(22-1)) | Y8: =Assumptions!$B$7*(1+0.0018*(23-1)) | Z8: =Assumptions!$B$7*(1+0.0018*(24-1)) | AA8: =Assumptions!$B$7*(1+0.0018*(25-1)) | AB8: =Assumptions!$B$7*(1+0.0018*(26-1)) | AC8: =Assumptions!$B$7*(1+0.0018*(27-1)) | AD8: =Assumptions!$B$7*(1+0.0018*(28-1)) | AE8: =Assumptions!$B$7*(1+0.0018*(29-1)) | AF8: =Assumptions!$B$7*(1+0.0018*(30-1)) | AG8: =Assumptions!$B$7*(1+0.0018*(31-1)) | AH8: =Assumptions!$B$7*(1+0.0018*(32-1)) | AI8: =Assumptions!$B$7*(1+0.0018*(33-1)) | AJ8: =Assumptions!$B$7*(1+0.0018*(34-1)) | AK8: =Assumptions!$B$7*(1+0.0018*(35-1)) | AL8: =Assumptions!$B$7*(1+0.0018*(36-1)) | AM8: =Assumptions!$B$7*(1+0.0018*(37-1)) | AN8: =Assumptions!$B$7*(1+0.0018*(38-1)) | AO8: =Assumptions!$B$7*(1+0.0018*(39-1)) | AP8: =Assumptions!$B$7*(1+0.0018*(40-1)) | AQ8: =Assumptions!$B$7*(1+0.0018*(41-1)) | AR8: =Assumptions!$B$7*(1+0.0018*(42-1)) | AS8: =Assumptions!$B$7*(1+0.0018*(43-1)) | AT8: =Assumptions!$B$7*(1+0.0018*(44-1)) | AU8: =Assumptions!$B$7*(1+0.0018*(45-1)) | AV8: =Assumptions!$B$7*(1+0.0018*(46-1)) | AW8: =Assumptions!$B$7*(1+0.0018*(47-1)) | AX8: =Assumptions!$B$7*(1+0.0018*(48-1))
A9: Subscription revenue | B9: INR | C9: =C7*C8 | D9: =D7*D8 | E9: =E7*E8 | F9: =F7*F8 | G9: =G7*G8 | H9: =H7*H8 | I9: =I7*I8 | J9: =J7*J8 | ... AX9: =AX7*AX8
A10: Add-on revenue | B10: INR | C10: =C7*Assumptions!$B$8*Assumptions!$B$9 | D10: =D7*Assumptions!$B$8*Assumptions!$B$9 | E10: =E7*Assumptions!$B$8*Assumptions!$B$9 | F10: =F7*Assumptions!$B$8*Assumptions!$B$9 | G10: =G7*Assumptions!$B$8*Assumptions!$B$9 | H10: =H7*Assumptions!$B$8*Assumptions!$B$9 | I10: =I7*Assumptions!$B$8*Assumptions!$B$9 | J10: =J7*Assumptions!$B$8*Assumptions!$B$9 | ... AX10: =AX7*Assumptions!$B$8*Assumptions!$B$9
A11: TOTAL REVENUE | B11: INR | C11: =C9+C10 | D11: =D9+D10 | E11: =E9+E10 | F11: =F9+F10 | G11: =G9+G10 | H11: =H9+H10 | I11: =I9+I10 | J11: =J9+J10 | ... AX11: =AX9+AX10
A12: Infrastructure | B12: INR | C12: =60000+C7*28 | D12: =60000+D7*28 | E12: =60000+E7*28 | F12: =60000+F7*28 | G12: =60000+G7*28 | H12: =60000+H7*28 | I12: =60000+I7*28 | J12: =60000+J7*28 | ... AX12: =60000+AX7*28
A13: Payment fees | B13: INR | C13: =C11*(Assumptions!$B$12*Assumptions!$B$14+Assumptions!$B$13*(1-Assumptions!$B$14)+Assumptions!$B$16) | D13: =D11*(Assumptions!$B$12*Assumptions!$B$14+Assumptions!$B$13*(1-Assumptions!$B$14)+Assumptions!$B$16) | E13: =E11*(Assumptions!$B$12*Assumptions!$B$14+Assumptions!$B$13*(1-Assumptions!$B$14)+Assumptions!$B$16) | F13: =F11*(Assumptions!$B$12*Assumptions!$B$14+Assumptions!$B$13*(1-Assumptions!$B$14)+Assumptions!$B$16) | G13: =G11*(Assumptions!$B$12*Assumptions!$B$14+Assumptions!$B$13*(1-Assumptions!$B$14)+Assumptions!$B$16) | H13: =H11*(Assumptions!$B$12*Assumptions!$B$14+Assumptions!$B$13*(1-Assumptions!$B$14)+Assumptions!$B$16) | I13: =I11*(Assumptions!$B$12*Assumptions!$B$14+Assumptions!$B$13*(1-Assumptions!$B$14)+Assumptions!$B$16) | J13: =J11*(Assumptions!$B$12*Assumptions!$B$14+Assumptions!$B$13*(1-Assumptions!$B$14)+Assumptions!$B$16) | ... AX13: =AX11*(Assumptions!$B$12*Assumptions!$B$14+Assumptions!$B$13*(1-Assumptions!$B$14)+Assumptions!$B$16)
A14: Support tooling | B14: INR | C14: =C7*Assumptions!$B$18 | D14: =D7*Assumptions!$B$18 | E14: =E7*Assumptions!$B$18 | F14: =F7*Assumptions!$B$18 | G14: =G7*Assumptions!$B$18 | H14: =H7*Assumptions!$B$18 | I14: =I7*Assumptions!$B$18 | J14: =J7*Assumptions!$B$18 | ... AX14: =AX7*Assumptions!$B$18
A15: GROSS PROFIT | B15: INR | C15: =C11-C12-C13-C14 | D15: =D11-D12-D13-D14 | E15: =E11-E12-E13-E14 | F15: =F11-F12-F13-F14 | G15: =G11-G12-G13-G14 | H15: =H11-H12-H13-H14 | I15: =I11-I12-I13-I14 | J15: =J11-J12-J13-J14 | ... AX15: =AX11-AX12-AX13-AX14
A16: Team cost | B16: INR | C16: =Team_Costs!$G$22 | D16: =Team_Costs!$G$22 | E16: =Team_Costs!$G$22 | F16: =Team_Costs!$G$22 | G16: =Team_Costs!$G$22 | H16: =Team_Costs!$G$22 | I16: =Team_Costs!$H$22 | J16: =Team_Costs!$H$22 | K16: =Team_Costs!$H$22 | L16: =Team_Costs!$H$22 | M16: =Team_Costs!$H$22 | N16: =Team_Costs!$H$22 | O16: =Team_Costs!$I$22 | P16: =Team_Costs!$I$22 | Q16: =Team_Costs!$I$22 | R16: =Team_Costs!$I$22 | S16: =Team_Costs!$I$22 | T16: =Team_Costs!$I$22 | U16: =Team_Costs!$I$22 | V16: =Team_Costs!$I$22 | ... Z16: =Team_Costs!$I$22 | AA16: =Team_Costs!B26 | AB16: =Team_Costs!B26 | AC16: =Team_Costs!B26 | AD16: =Team_Costs!B26 | AE16: =Team_Costs!B26 | AF16: =Team_Costs!B26 | AG16: =Team_Costs!B26 | AH16: =Team_Costs!B26 | AI16: =Team_Costs!B26 | AJ16: =Team_Costs!B26 | AK16: =Team_Costs!B26 | AL16: =Team_Costs!B26 | AM16: =Team_Costs!B26 | AN16: =Team_Costs!B26 | AO16: =Team_Costs!B26 | AP16: =Team_Costs!B26 | AQ16: =Team_Costs!B26 | AR16: =Team_Costs!B26 | AS16: =Team_Costs!B26 | AT16: =Team_Costs!B26 | AU16: =Team_Costs!B26 | AV16: =Team_Costs!B26 | AW16: =Team_Costs!B26 | AX16: =Team_Costs!B26
A17: Tools & subscriptions | B17: INR | C17: =Tools_Subscriptions!$E$25/12 | D17: =Tools_Subscriptions!$E$25/12 | E17: =Tools_Subscriptions!$E$25/12 | F17: =Tools_Subscriptions!$E$25/12 | G17: =Tools_Subscriptions!$E$25/12 | H17: =Tools_Subscriptions!$E$25/12 | I17: =Tools_Subscriptions!$E$25/12 | J17: =Tools_Subscriptions!$E$25/12 | ... AX17: =Tools_Subscriptions!$E$25/12
A18: Marketing & CAC | B18: INR | C18: =C5*Assumptions!$B$20+100000 | D18: =D5*Assumptions!$B$20+100000 | E18: =E5*Assumptions!$B$20+100000 | F18: =F5*Assumptions!$B$20+100000 | G18: =G5*Assumptions!$B$20+100000 | H18: =H5*Assumptions!$B$20+100000 | I18: =I5*Assumptions!$B$20+100000 | J18: =J5*Assumptions!$B$20+100000 | ... AX18: =AX5*Assumptions!$B$20+100000
A19: Compliance & legal | B19: INR | C19: =Payments_Fees!$D$21/12 | D19: =Payments_Fees!$D$21/12 | E19: =Payments_Fees!$D$21/12 | F19: =Payments_Fees!$D$21/12 | G19: =Payments_Fees!$D$21/12 | H19: =Payments_Fees!$D$21/12 | I19: =Payments_Fees!$D$21/12 | J19: =Payments_Fees!$D$21/12 | ... AX19: =Payments_Fees!$D$21/12
A20: TOTAL OPEX | B20: INR | C20: =SUM(C16:C19) | D20: =SUM(D16:D19) | E20: =SUM(E16:E19) | F20: =SUM(F16:F19) | G20: =SUM(G16:G19) | H20: =SUM(H16:H19) | I20: =SUM(I16:I19) | J20: =SUM(J16:J19) | ... AX20: =SUM(AX16:AX19)
A21: EBITDA | B21: INR | C21: =C15-C20 | D21: =D15-D20 | E21: =E15-E20 | F21: =F15-F20 | G21: =G15-G20 | H21: =H15-H20 | I21: =I15-I20 | J21: =J15-J20 | ... AX21: =AX15-AX20
A22: Funding inflow | B22: INR | C22: 50000000 | D22: 0 | E22: 0 | F22: 0 | G22: 0 | H22: 0 | I22: 0 | J22: 0 | K22: 0 | L22: 0 | M22: 0 | N22: 0 | O22: 0 | P22: 0 | Q22: 0 | R22: 0 | S22: 0 | T22: 0 | U22: 0 | V22: 25000000 | W22: 0 | X22: 0 | Y22: 0 | Z22: 0 | AA22: 0 | AB22: 0 | AC22: 0 | AD22: 0 | AE22: 0 | AF22: 0 | AG22: 0 | AH22: 0 | AI22: 0 | AJ22: 0 | AK22: 0 | AL22: 0 | AM22: 0 | AN22: 0 | AO22: 0 | AP22: 0 | AQ22: 0 | AR22: 0 | AS22: 0 | AT22: 0 | AU22: 0 | AV22: 0 | AW22: 0 | AX22: 0
A23: Cash balance | B23: INR | C23: =Assumptions!$B$27+C21+C22 | D23: =C23+D21+D22 | E23: =D23+E21+E22 | F23: =E23+F21+F22 | G23: =F23+G21+G22 | H23: =G23+H21+H22 | I23: =H23+I21+I22 | J23: =I23+J21+J22 | K23: =J23+K21+K22 | ... AX23: =AW23+AX21+AX22
A24: Runway (months) | B24: months | C24: =IF(C21>=0,"profitable",IF(C23<=0,"funding needed",C23/-C21)) | D24: =IF(D21>=0,"profitable",IF(D23<=0,"funding needed",D23/-D21)) | E24: =IF(E21>=0,"profitable",IF(E23<=0,"funding needed",E23/-E21)) | F24: =IF(F21>=0,"profitable",IF(F23<=0,"funding needed",F23/-F21)) | G24: =IF(G21>=0,"profitable",IF(G23<=0,"funding needed",G23/-G21)) | H24: =IF(H21>=0,"profitable",IF(H23<=0,"funding needed",H23/-H21)) | I24: =IF(I21>=0,"profitable",IF(I23<=0,"funding needed",I23/-I21)) | J24: =IF(J21>=0,"profitable",IF(J23<=0,"funding needed",J23/-J21)) | ... AX24: =IF(AX21>=0,"profitable",IF(AX23<=0,"funding needed",AX23/-AX21))
A26: Yellow = editable input. Funding plan: ₹1 Cr founder capital at M0, ₹5 Cr seed at M1, ₹2.5 Cr bridge at M20. Edit the Funding inflow row to model a different path.
A27: Support tooling (₹55/org) excludes support salaries, which are already inside Team cost — counting both would double-count the same rupees.
A28: Churn and ARPU are modelled explicitly here (rows 6 and 8) rather than taken from the Assumptions sheet, because retention improves and prices rise as the customer base matures.

Sheet Scenarios
A1: Growth Scenarios — 10K to 10M Users
A2: Annualised snapshot at each stage. Metrics mirror business/SCALABILITY_PLAN.md.
A4: Metric | B4: 10K users | C4: 100K users | D4: 1M users | E4: 10M users
A5: Registered users | B5: 10000 | C5: 100000 | D5: 1000000 | E5: 10000000
A6: Organizations | B6: =B5/Assumptions!$B$6 | C6: =C5/Assumptions!$B$6 | D6: =D5/Assumptions!$B$6 | E6: =E5/Assumptions!$B$6
A7: ARPU (INR/month) | B7: =Assumptions!$B$7*1.08 | C7: =Assumptions!$B$7*1.08 | D7: =Assumptions!$B$7*1.08 | E7: =Assumptions!$B$7*1.08
A8: Monthly revenue | B8: =B6*B7 | C8: =C6*C7 | D8: =D6*D7 | E8: =E6*E7
A9: Annual revenue (ARR) | B9: =B8*12 | C9: =C8*12 | D9: =D8*12 | E9: =E8*12
A10: Annual infrastructure | B10: 2217600 | C10: 22680000 | D10: 173376000 | E10: 1380960000
A11: Annual support tooling | B11: =B6*Assumptions!$B$18*12 | C11: =C6*Assumptions!$B$18*12 | D11: =D6*Assumptions!$B$18*12 | E11: =E6*Assumptions!$B$18*12
A12: Annual team cost | B12: 44000000 | C12: 90000000 | D12: 350000000 | E12: 1100000000
A13: Annual marketing & sales | B13: 10000000 | C13: 60000000 | D13: 1900000000 | E13: 26000000000
A14: Annual EBITDA | B14: =B9-B10-B11-B12-B13 | C14: =C9-C10-C11-C12-C13 | D14: =D9-D10-D11-D12-D13 | E14: =E9-E10-E11-E12-E13
A15: EBITDA margin | B15: =B14/B9 | C15: =C14/C9 | D15: =D14/D9 | E15: =E14/E9
A16: Infrastructure as % of revenue | B16: =B10/B9 | C16: =C10/C9 | D16: =D10/D9 | E16: =E10/E9
A17: Sessions / month | B17: 490909 | C17: 4909091 | D17: 49090909 | E17: 490909091
A18: Infrastructure cost / session (INR) | B18: =B10/12/B17 | C18: =C10/12/C17 | D18: =D10/12/D17 | E18: =E10/12/E17
A22: What must change to reach each stage
A23: Stage | B23: Database | C23: Storage | D23: Compute | E23: Key risk
A24: 10K users | B24: M30–M40 single region | C24: Lifecycle rules, ~30 TB | D24: Serverless | E24: Storage cost discipline
A25: 100K users | B25: M60 + cross-region replica | C25: CDN + variants, ~300 TB | D25: Serverless + workers | E25: Seasonal peaks
A26: 1M users | B26: Sharded M80+ multi-region | C26: Tiered to archive, ~3 PB | D26: Containers + edge | E26: Cost of egress
A27: 10M users | B27: Sharded, region-pinned | C27: ~30 PB, aggressive retention | D27: Multi-region active-active | E27: Retention economics
A30: Read the 1M and 10M columns as arithmetic, not as a forecast. The addressable market for professional photo-booth operators in India + GCC + SEA is realistically 50,000–100,000 organizations, so Stage 2 is the practical ceiling and Stage 3–4 require new geographies or adjacent products. They are included because investors ask, not because we plan to reach them.

Sheet Actual_vs_Forecast
A1: Actual vs Forecast
A2: Fill the Actual column monthly. Variance updates automatically.
A4: Month | B4: Forecast revenue | C4: Actual revenue | D4: Variance | E4: Variance % | F4: Notes
A5: M1 | B5: =Monthly_Forecast!C11 | D5: =IF(C5="","",C5-B5) | E5: =IF(C5="","",(C5-B5)/MAX(1,B5))
A6: M2 | B6: =Monthly_Forecast!D11 | D6: =IF(C6="","",C6-B6) | E6: =IF(C6="","",(C6-B6)/MAX(1,B6))
A7: M3 | B7: =Monthly_Forecast!E11 | D7: =IF(C7="","",C7-B7) | E7: =IF(C7="","",(C7-B7)/MAX(1,B7))
A8: M4 | B8: =Monthly_Forecast!F11 | D8: =IF(C8="","",C8-B8) | E8: =IF(C8="","",(C8-B8)/MAX(1,B8))
A9: M5 | B9: =Monthly_Forecast!G11 | D9: =IF(C9="","",C9-B9) | E9: =IF(C9="","",(C9-B9)/MAX(1,B9))
A10: M6 | B10: =Monthly_Forecast!H11 | D10: =IF(C10="","",C10-B10) | E10: =IF(C10="","",(C10-B10)/MAX(1,B10))
A11: M7 | B11: =Monthly_Forecast!I11 | D11: =IF(C11="","",C11-B11) | E11: =IF(C11="","",(C11-B11)/MAX(1,B11))
A12: M8 | B12: =Monthly_Forecast!J11 | D12: =IF(C12="","",C12-B12) | E12: =IF(C12="","",(C12-B12)/MAX(1,B12))
A13: M9 | B13: =Monthly_Forecast!K11 | D13: =IF(C13="","",C13-B13) | E13: =IF(C13="","",(C13-B13)/MAX(1,B13))
A14: M10 | B14: =Monthly_Forecast!L11 | D14: =IF(C14="","",C14-B14) | E14: =IF(C14="","",(C14-B14)/MAX(1,B14))
A15: M11 | B15: =Monthly_Forecast!M11 | D15: =IF(C15="","",C15-B15) | E15: =IF(C15="","",(C15-B15)/MAX(1,B15))
A16: M12 | B16: =Monthly_Forecast!N11 | D16: =IF(C16="","",C16-B16) | E16: =IF(C16="","",(C16-B16)/MAX(1,B16))
