Workbook

Sheet README
A1: Unit Economics — README
A2: HappyPix V2 · prepared 2026-10-23 · INR unless stated · planning estimates, not audited
B4: HappyPix — Revenue, Pricing & Unit Economics
B5: Companion to FINANCIAL_MODEL.xlsx and business/SCALABILITY_PLAN.md
B7: Purpose
B8: Answer three questions: what does a customer pay, what does that customer cost, and how
B9: many customers are needed before the business stops consuming cash.
B11: Sheet guide
B12: Assumptions — every input (prices, mix, costs, churn, CAC).
B13: Pricing — plan catalogue across four billing periods, net of payment fees.
B14: Customers — funnel, lifetime, LTV:CAC and payback.
B15: Cost_Per_Unit — cost and margin per session, per print, per photo, per AI call.
B16: Margins — contribution, blended margin, break-even, churn sensitivity.
B17: BreakEven — break-even org count and MRR, with pricing scenarios.
... B30: Print revenue is operator revenue, not platform revenue — it is shown separately and clearly labelled.

Sheet Assumptions
A1: Unit Economics — Assumptions
A2: Change yellow cells only.
A4: Input | B4: Value | C4: Unit | D4: Rationale
A5: FX rate | B5: 84 | C5: INR/USD | D5: Planning rate
A6: Basic plan (monthly) | B6: 1099 | C6: INR | D6: Catalogue
A7: Pro plan (monthly) | B7: 1299 | C7: INR | D7: Catalogue
A8: Premium plan (monthly) | B8: 1499 | C8: INR | D8: Catalogue
A9: Plan mix — Basic | B9: 0.45 | C9: % of orgs | D9: Long tail of small operators
A10: Plan mix — Pro | B10: 0.4 | C10: % of orgs | D10: Core wedding operators
A11: Plan mix — Premium | B11: 0.15 | C11: % of orgs | D11: Fleets and rental businesses
A12: Annual billing share | B12: 0.35 | C12: % of orgs | D12: Discount is 9–20% by period
A13: Payment MDR (blended) | B13: 0.013 | C13: % of value | D13: Cards 2% × 35% + UPI 0%
A14: GST rate | B14: 0.18 | C14: % | D14: India
A15: Monthly logo churn | B15: 0.028 | C15: % of orgs | D15: Year-one blended
A16: Events per org per month | B16: 1.2 | C16: events | D16: Booking frequency
... A34: Fixed opex per month | B34: 3900000 | C34: INR | D34: Steady-state team (Phase D) + tools + compliance

Sheet Pricing
A1: Pricing & Plan Economics
A2: Catalogue prices, effective per-month rates, and revenue net of fees.
A4: Plan | B4: Monthly | C4: Quarterly | D4: 6-month | E4: Annual | F4: Annual per month | G4: Discount vs monthly | H4: Net of fees (monthly) | I4: Notes
A5: Free Trial | B5: 0 | C5: 0 | D5: 0 | E5: 0 | F5: =IF(E5="","",E5/12) | G5: =IF(B5=0,"",1-(F5/B5)) | H5: =B5*(1-Assumptions!$B$13) | I5: 14 days · 1 device · 1 event
A6: Basic | B6: 1099 | C6: 2847 | D6: 4794 | E6: 5988 | F6: =IF(E6="","",E6/12) | G6: =IF(B6=0,"",1-(F6/B6)) | H6: =B6*(1-Assumptions!$B$13) | I6: 2 devices · 2 parallel events · 25 AI credits
A7: Pro | B7: 1299 | C7: 3447 | D7: 5994 | E7: 8388 | F7: =IF(E7="","",E7/12) | G7: =IF(B7=0,"",1-(F7/B7)) | H7: =B7*(1-Assumptions!$B$13) | I7: 2 devices · 4 events · 250 credits
A8: Premium | B8: 1499 | C8: 3897 | D8: 6594 | E8: 9588 | F8: =IF(E8="","",E8/12) | G8: =IF(B8=0,"",1-(F8/B8)) | H8: =B8*(1-Assumptions!$B$13) | I8: 2 devices · 8 events · 500 credits
A9: Enterprise | F9: =IF(E9="","",E9/12) | G9: =IF(B9=0,"",1-(F9/B9)) | H9: =B9*(1-Assumptions!$B$13) | I9: Custom · 25 devices · 20 events
A11: GST (18%) is added on top at checkout and is not revenue. Net-of-fees subtracts the blended MDR only.

Sheet Customers
A1: Customer Funnel, Retention & Lifetime Value
A2: Cohort economics: what a customer is worth and how long they stay.
A4: Metric | B4: Value | C4: Unit | D4: How it is calculated
A5: Website visitors / month | B5: 25000
A6: Trial signups | B6: =B5*0.04 | D6: 4% of visitors start a trial
A7: Paid conversions | B7: =B6*Assumptions!$B$31 | D7: Trial conversion applied
A8: Blended ARPU | B8: =Assumptions!$B$6*Assumptions!$B$9+Assumptions!$B$7*Assumptions!$B$10+Assumptions!$B$8*Assumptions!$B$11
A9: Average lifetime (months) | B9: =1/Assumptions!$B$15
A10: Gross revenue per customer (lifetime) | B10: =B8*B9
A11: Service cost per customer per month | B11: =Assumptions!$B$29+Assumptions!$B$25*Assumptions!$B$16*Assumptions!$B$17+Assumptions!$B$28*Assumptions!$B$27
A12: Contribution per customer per month | B12: =B8*(1-Assumptions!$B$13)-B11
A13: LTV (contribution basis) | B13: =B12*B9
A14: CAC | B14: =Assumptions!$B$30
A15: LTV : CAC | B15: =B13/B14 | D15: Target ≥ 3.0 for a healthy SaaS; below 2.0 requires fixing acquisition cost
A16: CAC payback (months) | B16: =B14/B12 | D16: Target < 12 months
A17: Net revenue retention (annual) | B17: 0.96 | D17: Expansion 0.8%/mo vs churn 2.8%/mo — below 100% means growth depends on new logos

Sheet Cost_Per_Unit
A1: Cost Per Unit — Event, Booth, Session, Photo, Print, AI
A2: The numbers that must stay below price for the business to work.
A4: Unit | B4: Cost (INR) | C4: Revenue attached (INR) | D4: Margin | E4: Calculation
A5: Per session (infrastructure) | B5: =Assumptions!$B$25+Assumptions!$B$26 | C5: =(Customers!$B$8/(Assumptions!$B$16*Assumptions!$B$17)) | D5: =C5-B5 | E5: Subscription revenue attributed per session
A6: Per printed sheet — 4×6 | B6: =Assumptions!$B$19 | C6: 250 | D6: =C6-B6 | E6: Guest pays for the print; media is the dominant cost
A7: Per printed sheet — 6×8 | B7: =Assumptions!$B$20 | C7: 400 | D7: =C7-B7 | E7: Premium event pricing
A8: Per printed sheet — 8×10 | B8: =Assumptions!$B$21 | C8: 650 | D8: =C8-B8 | E8: Large format; watch waste rates
A9: Blended media cost per print | B9: =Assumptions!$B$19*Assumptions!$B$22+Assumptions!$B$20*Assumptions!$B$23+Assumptions!$B$21*Assumptions!$B$24 | E9: Weighted by layout mix
A10: Media cost per event | B10: =B9*Assumptions!$B$17*Assumptions!$B$18 | E10: 90 sessions × 85% printing
A11: AI cost per org per month | B11: =Assumptions!$B$28*Assumptions!$B$27 | E11: Template generation is credit-capped per plan
A12: Storage cost per photo (monthly) | B12: 0.006 | E12: Tiered assumption: 1.1 MB average at ~₹5.5/GB handwaved across classes
A13: Service cost per org per month | B13: =Assumptions!$B$29+B5*Assumptions!$B$16*Assumptions!$B$17+B12*0 | E13: Support + infrastructure + AI + storage
A15: Print-based revenue (optional add-on for operators who sell prints at the booth)
A16: Prints sold per event | B16: =Assumptions!$B$17*Assumptions!$B$18
A17: Gross print revenue per event | B17: =B16*C6
A18: Media cost per event | B18: =B16*B9
A19: Print contribution per event | B19: =B17-B18

Sheet Margins
A1: Margins & Contribution
A2: Unit margin, blended gross margin and the path to positive EBITDA.
A4: Metric | B4: Value | C4: Unit | D4: Notes
A5: Blended ARPU | B5: =Customers!$B$8
A6: Payment fees per org | B6: =B5*Assumptions!$B$13 | D6: Blended MDR across cards and UPI
A7: Variable service cost per org | B7: =Assumptions!$B$29+Assumptions!$B$25*Assumptions!$B$16*Assumptions!$B$17+Assumptions!$B$28*Assumptions!$B$27 | D7: Support + infrastructure + AI
A8: Contribution per org per month | B8: =B5-B6-B7
A9: Contribution margin | B9: =B8/B5 | D9: Target > 80% for a software+media hybrid
A11: Fixed opex per month | B11: =Assumptions!$B$34
A12: Break-even organizations | B12: =B11/B8 | D12: Paying organizations required to cover fixed costs
A13: Break-even MRR | B13: =B12*B5
A14: Break-even ARR | B14: =B13*12
A16: Sensitivity: contribution margin vs churn
A17: Monthly churn | B17: Lifetime (months) | C17: LTV (INR) | D17: LTV : CAC
A18: 0.02 | B18: =1/A18 | C18: =B8*B18 | D18: =C18/Assumptions!$B$30
A19: 0.025 | B19: =1/A19 | C19: =B8*B19 | D19: =C19/Assumptions!$B$30
A20: 0.028 | B20: =1/A20 | C20: =B8*B20 | D20: =C20/Assumptions!$B$30
A21: 0.035 | B21: =1/A21 | C21: =B8*B21 | D21: =C21/Assumptions!$B$30
A22: 0.045 | B22: =1/A22 | C22: =B8*B22 | D22: =C22/Assumptions!$B$30
A23: 0.06 | B23: =1/A23 | C23: =B8*B23 | D23: =C23/Assumptions!$B$30

Sheet BreakEven
A1: Break-Even Analysis
A2: When the business stops consuming cash.
A4: Item | B4: Value | C4: Unit | D4: Note
A5: Contribution per org per month | B5: =Margins!$B$8
A6: Fixed opex per month | B6: =Assumptions!$B$34
A7: Paying orgs to break even | B7: =B6/Margins!$B$8
A8: Months to reach that org count | B8: 22 | D8: From the Monthly_Forecast ramp with current CAC and churn
A9: New orgs needed per month at steady state | B9: =B7*Assumptions!$B$15 | D9: Replacement rate — growth beyond this is net new
A11: Break-even under different pricing
A12: Scenario | B12: ARPU (INR) | C12: Break-even orgs | D12: Comment
A13: Current blended | B13: =Margins!$B$5 | C13: =B6/(B13*(1-Assumptions!$B$13)-Margins!$B$7) | D13: As modelled
A14: +10% price | B14: =Margins!$B$5*1.1 | C14: =B6/(B14*(1-Assumptions!$B$13)-Margins!$B$7) | D14: Small churn risk
A15: −10% price | B15: =Margins!$B$5*0.9 | C15: =B6/(B15*(1-Assumptions!$B$13)-Margins!$B$7) | D15: Needs volume
A16: Premium-heavy mix | B16: 1420 | C16: =B6/(B16*(1-Assumptions!$B$13)-Margins!$B$7) | D16: Higher touch support

Sheet Sensitivity
A1: Sensitivity Analysis
A2: Which lever moves the outcome most.
A4: Lever | B4: Low | C4: Base | D4: High | E4: Effect | F4: Interpretation
A5: Monthly churn | B5: 0.018 | C5: 0.028 | D5: 0.045 | E5: LTV | F5: Every 1pt of churn is worth ~5 months of revenue
A6: Events per org / month | B6: 1 | C6: 1.2 | D6: 1.6 | E6: Media + infra cost | F6: More events = more prints but also more support
A7: Sessions per event | B7: 60 | C7: 90 | D7: 140 | E7: Infra + media | F7: Cost scales linearly; price usually does not
A8: Digital download rate | B8: 0.25 | C8: 0.35 | D8: 0.6 | E8: Egress | F8: Variants + CDN are the mitigation
A9: Photo retention (months) | B9: 6 | C9: 24 | D9: 60 | E9: Storage cost | F9: The single largest long-term cost lever
A10: AI generations / org | B10: 1 | C10: 3 | D10: 8 | E10: AI cost | F10: Cap per plan; charge for extra credits
A11: CAC | B11: 4000 | C11: 6000 | D11: 9000 | E11: Payback | F11: Payback under 12 months is the target

Sheet Revenue_Forecast
A1: Revenue Forecast by Scenario
A2: Annual recurring revenue at each growth stage, with cost and margin.
A4: Metric | B4: 10K users | C4: 100K users | D4: 1M users | E4: 10M users
A5: Registered users | B5: 10000 | C5: 100000 | D5: 1000000 | E5: 10000000
A6: Organizations | B6: =B5/2.2 | C6: =C5/2.2 | D6: =D5/2.2 | E6: =E5/2.2
A7: ARPU (INR/month) | B7: =Customers!$B$8 | C7: =Customers!$B$8 | D7: =Customers!$B$8 | E7: =Customers!$B$8
A8: MRR | B8: =B6*B7 | C8: =C6*C7 | D8: =D6*D7 | E8: =E6*E7
A9: ARR | B9: =B8*12 | C9: =C8*12 | D9: =D8*12 | E9: =E8*12
A10: Annual infrastructure | B10: 2217600 | C10: 22680000 | D10: 173376000 | E10: 1380960000
A11: Annual support (tooling) | B11: =B6*Assumptions!$B$29*12 | C11: =C6*Assumptions!$B$29*12 | D11: =D6*Assumptions!$B$29*12 | E11: =E6*Assumptions!$B$29*12
A12: Annual team | B12: 44000000 | C12: 90000000 | D12: 350000000 | E12: 1100000000
A13: Annual marketing | B13: 10000000 | C13: 60000000 | D13: 1900000000 | E13: 26000000000
A14: EBITDA | B14: =B9-B10-B11-B12-B13 | C14: =C9-C10-C11-C12-C13 | D14: =D9-D10-D11-D12-D13 | E14: =E9-E10-E11-E12-E13
A15: EBITDA margin | B15: =B14/B9 | C15: =C14/C9 | D15: =D14/D9 | E15: =E14/E9
A16: Gross margin (after infra + support) | B16: =(B9-B10-B11)/B9 | C16: =(C9-C10-C11)/C9 | D16: =(D9-D10-D11)/D9 | E16: =(E9-E10-E11)/E9
A18: Support here is tooling only; support salaries sit in the team line. If self-service adoption is weak, add ₹250/org/month to support and EBITDA falls by that amount × organizations.
